Workbook

Sheet Dashboard
A1: Personal Budget Dashboard

Sheet Transactions
A1: Date | B1: Description | C1: Amount | D1: Category | E1: Type | F1: Month
A2: 2025-01-01 | B2: Rent Payment - Sunrise Apartments | C2: -1450 | D2: Housing | E2: Expense | F2: 2025-01
A3: 2025-01-01 | B3: Employer Payroll Direct Dep | C3: 2650 | D3: Income | E3: Income | F3: 2025-01
A4: 2025-01-01 | B4: Local Pizza Co | C4: -25.13 | D4: Dining Out | E4: Expense | F4: 2025-01
A5: 2025-01-03 | B5: Geico Insurance | C5: -135.25 | D5: Insurance | E5: Expense | F5: 2025-01
A6: 2025-01-04 | B6: Planet Fitness | C6: -24.99 | D6: Health & Fitness | E6: Expense | F6: 2025-01
A7: 2025-01-05 | B7: Netflix.com | C7: -15.49 | D7: Subscriptions | E7: Expense | F7: 2025-01
A8: 2025-01-05 | B8: Airbnb | C8: -257.17 | D8: Travel | E8: Expense | F8: 2025-01
A9: 2025-01-05 | B9: Ticketmaster | C9: -81.98 | D9: Entertainment | E9: Expense | F9: 2025-01
A10: 2025-01-06 | B10: Best Buy | C10: -292.19 | D10: Shopping | E10: Expense | F10: 2025-01
A11: 2025-01-06 | B11: Trader Joe's | C11: -69.22 | D11: Groceries | E11: Expense | F11: 2025-01
A12: 2025-01-06 | B12: The Cheesecake Factory | C12: -62.27 | D12: Dining Out | E12: Expense | F12: 2025-01
A13: 2025-01-07 | B13: Spotify USA | C13: -11.99 | D13: Subscriptions | E13: Expense | F13: 2025-01
... A351: 2025-06-29 | B351: Chase Credit Card Payment | C351: -280.15 | D351: Debt Payments | E351: Expense | F351: 2025-06

Sheet Monthly Summary
A3: Category | B3: 2025-01 | C3: 2025-02 | D3: 2025-03 | E3: 2025-04 | F3: 2025-05 | G3: 2025-06 | H3: Total
A4: Cash & Misc | B4: =-SUMIFS(Transactions!$C$2:$C$351,Transactions!$D$2:$D$351,$A4,Transactions!$F$2:$F$351,B$3) | C4: =-SUMIFS(Transactions!$C$2:$C$351,Transactions!$D$2:$D$351,$A4,Transactions!$F$2:$F$351,C$3) | D4: =-SUMIFS(Transactions!$C$2:$C$351,Transactions!$D$2:$D$351,$A4,Transactions!$F$2:$F$351,D$3) | E4: =-SUMIFS(Transactions!$C$2:$C$351,Transactions!$D$2:$D$351,$A4,Transactions!$F$2:$F$351,E$3) | F4: =-SUMIFS(Transactions!$C$2:$C$351,Transactions!$D$2:$D$351,$A4,Transactions!$F$2:$F$351,F$3) | G4: =-SUMIFS(Transactions!$C$2:$C$351,Transactions!$D$2:$D$351,$A4,Transactions!$F$2:$F$351,G$3) | H4: =SUM(B4:G4)
A5: Debt Payments | B5: =-SUMIFS(Transactions!$C$2:$C$351,Transactions!$D$2:$D$351,$A5,Transactions!$F$2:$F$351,B$3) | C5: =-SUMIFS(Transactions!$C$2:$C$351,Transactions!$D$2:$D$351,$A5,Transactions!$F$2:$F$351,C$3) | D5: =-SUMIFS(Transactions!$C$2:$C$351,Transactions!$D$2:$D$351,$A5,Transactions!$F$2:$F$351,D$3) | E5: =-SUMIFS(Transactions!$C$2:$C$351,Transactions!$D$2:$D$351,$A5,Transactions!$F$2:$F$351,E$3) | F5: =-SUMIFS(Transactions!$C$2:$C$351,Transactions!$D$2:$D$351,$A5,Transactions!$F$2:$F$351,F$3) | G5: =-SUMIFS(Transactions!$C$2:$C$351,Transactions!$D$2:$D$351,$A5,Transactions!$F$2:$F$351,G$3) | H5: =SUM(B5:G5)
A6: Dining Out | B6: =-SUMIFS(Transactions!$C$2:$C$351,Transactions!$D$2:$D$351,$A6,Transactions!$F$2:$F$351,B$3) | C6: =-SUMIFS(Transactions!$C$2:$C$351,Transactions!$D$2:$D$351,$A6,Transactions!$F$2:$F$351,C$3) | D6: =-SUMIFS(Transactions!$C$2:$C$351,Transactions!$D$2:$D$351,$A6,Transactions!$F$2:$F$351,D$3) | E6: =-SUMIFS(Transactions!$C$2:$C$351,Transactions!$D$2:$D$351,$A6,Transactions!$F$2:$F$351,E$3) | F6: =-SUMIFS(Transactions!$C$2:$C$351,Transactions!$D$2:$D$351,$A6,Transactions!$F$2:$F$351,F$3) | G6: =-SUMIFS(Transactions!$C$2:$C$351,Transactions!$D$2:$D$351,$A6,Transactions!$F$2:$F$351,G$3) | H6: =SUM(B6:G6)
A7: Entertainment | B7: =-SUMIFS(Transactions!$C$2:$C$351,Transactions!$D$2:$D$351,$A7,Transactions!$F$2:$F$351,B$3) | C7: =-SUMIFS(Transactions!$C$2:$C$351,Transactions!$D$2:$D$351,$A7,Transactions!$F$2:$F$351,C$3) | D7: =-SUMIFS(Transactions!$C$2:$C$351,Transactions!$D$2:$D$351,$A7,Transactions!$F$2:$F$351,D$3) | E7: =-SUMIFS(Transactions!$C$2:$C$351,Transactions!$D$2:$D$351,$A7,Transactions!$F$2:$F$351,E$3) | F7: =-SUMIFS(Transactions!$C$2:$C$351,Transactions!$D$2:$D$351,$A7,Transactions!$F$2:$F$351,F$3) | G7: =-SUMIFS(Transactions!$C$2:$C$351,Transactions!$D$2:$D$351,$A7,Transactions!$F$2:$F$351,G$3) | H7: =SUM(B7:G7)
A8: Groceries | B8: =-SUMIFS(Transactions!$C$2:$C$351,Transactions!$D$2:$D$351,$A8,Transactions!$F$2:$F$351,B$3) | C8: =-SUMIFS(Transactions!$C$2:$C$351,Transactions!$D$2:$D$351,$A8,Transactions!$F$2:$F$351,C$3) | D8: =-SUMIFS(Transactions!$C$2:$C$351,Transactions!$D$2:$D$351,$A8,Transactions!$F$2:$F$351,D$3) | E8: =-SUMIFS(Transactions!$C$2:$C$351,Transactions!$D$2:$D$351,$A8,Transactions!$F$2:$F$351,E$3) | F8: =-SUMIFS(Transactions!$C$2:$C$351,Transactions!$D$2:$D$351,$A8,Transactions!$F$2:$F$351,F$3) | G8: =-SUMIFS(Transactions!$C$2:$C$351,Transactions!$D$2:$D$351,$A8,Transactions!$F$2:$F$351,G$3) | H8: =SUM(B8:G8)
A9: Health & Fitness | B9: =-SUMIFS(Transactions!$C$2:$C$351,Transactions!$D$2:$D$351,$A9,Transactions!$F$2:$F$351,B$3) | C9: =-SUMIFS(Transactions!$C$2:$C$351,Transactions!$D$2:$D$351,$A9,Transactions!$F$2:$F$351,C$3) | D9: =-SUMIFS(Transactions!$C$2:$C$351,Transactions!$D$2:$D$351,$A9,Transactions!$F$2:$F$351,D$3) | E9: =-SUMIFS(Transactions!$C$2:$C$351,Transactions!$D$2:$D$351,$A9,Transactions!$F$2:$F$351,E$3) | F9: =-SUMIFS(Transactions!$C$2:$C$351,Transactions!$D$2:$D$351,$A9,Transactions!$F$2:$F$351,F$3) | G9: =-SUMIFS(Transactions!$C$2:$C$351,Transactions!$D$2:$D$351,$A9,Transactions!$F$2:$F$351,G$3) | H9: =SUM(B9:G9)
A10: Housing | B10: =-SUMIFS(Transactions!$C$2:$C$351,Transactions!$D$2:$D$351,$A10,Transactions!$F$2:$F$351,B$3) | C10: =-SUMIFS(Transactions!$C$2:$C$351,Transactions!$D$2:$D$351,$A10,Transactions!$F$2:$F$351,C$3) | D10: =-SUMIFS(Transactions!$C$2:$C$351,Transactions!$D$2:$D$351,$A10,Transactions!$F$2:$F$351,D$3) | E10: =-SUMIFS(Transactions!$C$2:$C$351,Transactions!$D$2:$D$351,$A10,Transactions!$F$2:$F$351,E$3) | F10: =-SUMIFS(Transactions!$C$2:$C$351,Transactions!$D$2:$D$351,$A10,Transactions!$F$2:$F$351,F$3) | G10: =-SUMIFS(Transactions!$C$2:$C$351,Transactions!$D$2:$D$351,$A10,Transactions!$F$2:$F$351,G$3) | H10: =SUM(B10:G10)
A11: Insurance | B11: =-SUMIFS(Transactions!$C$2:$C$351,Transactions!$D$2:$D$351,$A11,Transactions!$F$2:$F$351,B$3) | C11: =-SUMIFS(Transactions!$C$2:$C$351,Transactions!$D$2:$D$351,$A11,Transactions!$F$2:$F$351,C$3) | D11: =-SUMIFS(Transactions!$C$2:$C$351,Transactions!$D$2:$D$351,$A11,Transactions!$F$2:$F$351,D$3) | E11: =-SUMIFS(Transactions!$C$2:$C$351,Transactions!$D$2:$D$351,$A11,Transactions!$F$2:$F$351,E$3) | F11: =-SUMIFS(Transactions!$C$2:$C$351,Transactions!$D$2:$D$351,$A11,Transactions!$F$2:$F$351,F$3) | G11: =-SUMIFS(Transactions!$C$2:$C$351,Transactions!$D$2:$D$351,$A11,Transactions!$F$2:$F$351,G$3) | H11: =SUM(B11:G11)
A12: Pets | B12: =-SUMIFS(Transactions!$C$2:$C$351,Transactions!$D$2:$D$351,$A12,Transactions!$F$2:$F$351,B$3) | C12: =-SUMIFS(Transactions!$C$2:$C$351,Transactions!$D$2:$D$351,$A12,Transactions!$F$2:$F$351,C$3) | D12: =-SUMIFS(Transactions!$C$2:$C$351,Transactions!$D$2:$D$351,$A12,Transactions!$F$2:$F$351,D$3) | E12: =-SUMIFS(Transactions!$C$2:$C$351,Transactions!$D$2:$D$351,$A12,Transactions!$F$2:$F$351,E$3) | F12: =-SUMIFS(Transactions!$C$2:$C$351,Transactions!$D$2:$D$351,$A12,Transactions!$F$2:$F$351,F$3) | G12: =-SUMIFS(Transactions!$C$2:$C$351,Transactions!$D$2:$D$351,$A12,Transactions!$F$2:$F$351,G$3) | H12: =SUM(B12:G12)
A13: Shopping | B13: =-SUMIFS(Transactions!$C$2:$C$351,Transactions!$D$2:$D$351,$A13,Transactions!$F$2:$F$351,B$3) | C13: =-SUMIFS(Transactions!$C$2:$C$351,Transactions!$D$2:$D$351,$A13,Transactions!$F$2:$F$351,C$3) | D13: =-SUMIFS(Transactions!$C$2:$C$351,Transactions!$D$2:$D$351,$A13,Transactions!$F$2:$F$351,D$3) | E13: =-SUMIFS(Transactions!$C$2:$C$351,Transactions!$D$2:$D$351,$A13,Transactions!$F$2:$F$351,E$3) | F13: =-SUMIFS(Transactions!$C$2:$C$351,Transactions!$D$2:$D$351,$A13,Transactions!$F$2:$F$351,F$3) | G13: =-SUMIFS(Transactions!$C$2:$C$351,Transactions!$D$2:$D$351,$A13,Transactions!$F$2:$F$351,G$3) | H13: =SUM(B13:G13)
A14: Subscriptions | B14: =-SUMIFS(Transactions!$C$2:$C$351,Transactions!$D$2:$D$351,$A14,Transactions!$F$2:$F$351,B$3) | C14: =-SUMIFS(Transactions!$C$2:$C$351,Transactions!$D$2:$D$351,$A14,Transactions!$F$2:$F$351,C$3) | D14: =-SUMIFS(Transactions!$C$2:$C$351,Transactions!$D$2:$D$351,$A14,Transactions!$F$2:$F$351,D$3) | E14: =-SUMIFS(Transactions!$C$2:$C$351,Transactions!$D$2:$D$351,$A14,Transactions!$F$2:$F$351,E$3) | F14: =-SUMIFS(Transactions!$C$2:$C$351,Transactions!$D$2:$D$351,$A14,Transactions!$F$2:$F$351,F$3) | G14: =-SUMIFS(Transactions!$C$2:$C$351,Transactions!$D$2:$D$351,$A14,Transactions!$F$2:$F$351,G$3) | H14: =SUM(B14:G14)
A15: Transportation | B15: =-SUMIFS(Transactions!$C$2:$C$351,Transactions!$D$2:$D$351,$A15,Transactions!$F$2:$F$351,B$3) | C15: =-SUMIFS(Transactions!$C$2:$C$351,Transactions!$D$2:$D$351,$A15,Transactions!$F$2:$F$351,C$3) | D15: =-SUMIFS(Transactions!$C$2:$C$351,Transactions!$D$2:$D$351,$A15,Transactions!$F$2:$F$351,D$3) | E15: =-SUMIFS(Transactions!$C$2:$C$351,Transactions!$D$2:$D$351,$A15,Transactions!$F$2:$F$351,E$3) | F15: =-SUMIFS(Transactions!$C$2:$C$351,Transactions!$D$2:$D$351,$A15,Transactions!$F$2:$F$351,F$3) | G15: =-SUMIFS(Transactions!$C$2:$C$351,Transactions!$D$2:$D$351,$A15,Transactions!$F$2:$F$351,G$3) | H15: =SUM(B15:G15)
... A17: Utilities | B17: =-SUMIFS(Transactions!$C$2:$C$351,Transactions!$D$2:$D$351,$A17,Transactions!$F$2:$F$351,B$3) | C17: =-SUMIFS(Transactions!$C$2:$C$351,Transactions!$D$2:$D$351,$A17,Transactions!$F$2:$F$351,C$3) | D17: =-SUMIFS(Transactions!$C$2:$C$351,Transactions!$D$2:$D$351,$A17,Transactions!$F$2:$F$351,D$3) | E17: =-SUMIFS(Transactions!$C$2:$C$351,Transactions!$D$2:$D$351,$A17,Transactions!$F$2:$F$351,E$3) | F17: =-SUMIFS(Transactions!$C$2:$C$351,Transactions!$D$2:$D$351,$A17,Transactions!$F$2:$F$351,F$3) | G17: =-SUMIFS(Transactions!$C$2:$C$351,Transactions!$D$2:$D$351,$A17,Transactions!$F$2:$F$351,G$3) | H17: =SUM(B17:G17)
A18: Total Spending | B18: =SUM(B4:B17) | C18: =SUM(C4:C17) | D18: =SUM(D4:D17) | E18: =SUM(E4:E17) | F18: =SUM(F4:F17) | G18: =SUM(G4:G17) | H18: =SUM(H4:H17)
A21: Income vs. Expenses vs. Savings
A22: Metric | B22: 2025-01 | C22: 2025-02 | D22: 2025-03 | E22: 2025-04 | F22: 2025-05 | G22: 2025-06
A23: Income | B23: =SUMIFS(Transactions!$C$2:$C$351,Transactions!$E$2:$E$351,"Income",Transactions!$F$2:$F$351,B$3) | C23: =SUMIFS(Transactions!$C$2:$C$351,Transactions!$E$2:$E$351,"Income",Transactions!$F$2:$F$351,C$3) | D23: =SUMIFS(Transactions!$C$2:$C$351,Transactions!$E$2:$E$351,"Income",Transactions!$F$2:$F$351,D$3) | E23: =SUMIFS(Transactions!$C$2:$C$351,Transactions!$E$2:$E$351,"Income",Transactions!$F$2:$F$351,E$3) | F23: =SUMIFS(Transactions!$C$2:$C$351,Transactions!$E$2:$E$351,"Income",Transactions!$F$2:$F$351,F$3) | G23: =SUMIFS(Transactions!$C$2:$C$351,Transactions!$E$2:$E$351,"Income",Transactions!$F$2:$F$351,G$3)
A24: Expenses | B24: =B18 | C24: =C18 | D24: =D18 | E24: =E18 | F24: =F18 | G24: =G18
A25: Net Savings | B25: =B23-B24 | C25: =C23-C24 | D25: =D23-D24 | E25: =E23-E24 | F25: =F23-F24 | G25: =G23-G24
A26: Savings Rate | B26: =IF(B23=0,0,B25/B23) | C26: =IF(C23=0,0,C25/C23) | D26: =IF(D23=0,0,D25/D23) | E26: =IF(E23=0,0,E25/E23) | F26: =IF(F23=0,0,F25/F23) | G26: =IF(G23=0,0,G25/G23)

Sheet Recurring Costs
A1: Detected Recurring Charges (3+ months)
A3: Description | B3: Occurrences | C3: Avg Amount | D3: Est. Annual Cost
A4: Rent Payment - Sunrise Apartments | B4: 6 | C4: 1450 | D4: 17400
A5: Chase Credit Card Payment | B5: 7 | C5: 371.34 | D5: 4456.05
A6: Southwest Airlines | B6: 8 | C6: 282 | D6: 3383.95
A7: Marriott Hotels | B7: 11 | C7: 222.25 | D7: 2667.01
A8: Student Loan Servicer | B8: 6 | C8: 220 | D8: 2640
A9: Airbnb | B9: 8 | C9: 210.85 | D9: 2530.24
A10: Best Buy | B10: 8 | C10: 157.62 | D10: 1891.38
A11: Geico Insurance | B11: 6 | C11: 136.65 | D11: 1639.8
A12: REI | B12: 7 | C12: 111.14 | D12: 1333.7
A13: PG&E Electric | B13: 6 | C13: 97.45 | D13: 1169.4
A14: Comcast Xfinity | B14: 6 | C14: 90.01 | D14: 1080.16
A15: Ticketmaster | B15: 7 | C15: 87.11 | D15: 1045.29
... A46: Starbucks | B46: 8 | C46: 7.62 | D46: 91.48
